{
  "LEVEL8A.PHD": [
    {
      "X": 30208,
      "Y": -256,
      "Z": 6656,
      "Room": -1
    },
    {
      "X": 30208,
      "Y": -256,
      "Z": 5632,
      "Room": -1
    },
    {
      "X": 31232,
      "Y": -256,
      "Z": 5632,
      "Room": -1
    },
    {
      "X": 31232,
      "Y": -256,
      "Z": 6656,
      "Room": -1
    },
    {
      "X": 31232,
      "Y": -256,
      "Z": 7680,
      "Room": -1
    },
    {
      "X": 32256,
      "Y": -256,
      "Z": 7680,
      "Room": -1
    },
    {
      "X": 32256,
      "Y": -256,
      "Z": 6656,
      "Room": -1
    },
    {
      "X": 34304,
      "Y": -256,
      "Z": 6656,
      "Room": -1
    },
    {
      "X": 35328,
      "Y": -256,
      "Z": 6656,
      "Room": -1
    },
    {
      "X": 35328,
      "Y": -256,
      "Z": 7680,
      "Room": -1
    },
    {
      "X": 36352,
      "Y": -256,
      "Z": 7680,
      "Room": -1
    },
    {
      "X": 36352,
      "Y": -256,
      "Z": 6656,
      "Room": -1
    },
    {
      "X": 36352,
      "Y": -256,
      "Z": 5632,
      "Room": -1
    },
    {
      "X": 37376,
      "Y": -256,
      "Z": 5632,
      "Room": -1
    },
    {
      "X": 37376,
      "Y": -256,
      "Z": 6656,
      "Room": -1
    }
  ]
}